xnxxdl/__init__.py
xnxxdl/main.py
xnxx_dl-0.0.6.dist-info/METADATA
xnxx_dl-0.0.6.dist-info/WHEEL
xnxx_dl-0.0.6.dist-info/entry_points.txt
xnxx_dl-0.0.6.dist-info/top_level.txt
xnxx_dl-0.0.6.dist-info/RECORD
