Metadata-Version: 2.1
Name: xnxx-dl
Version: 0.0.6
Summary: A web scraping and URL filtering tool for xnxx.com
Home-page: https://github.com/thisisawesome1994/xnxx-dl
Author: Joannes J.A. Wyckmans
Author-email: johan.wyckmans@gmail.com
Requires-Dist: requests
Requires-Dist: beautifulsoup4
Requires-Dist: urllib3
Requires-Dist: argparse
Requires-Dist: youtube-dl
